{
  "lakewood": {
    "label": "Lakewood, WA",
    "temp": 52,
    "condition": "Partly Sunny",
    "emoji": "\u26c5",
    "forecast": [
      {
        "name": "TOD",
        "high": 62,
        "precip": 27
      },
      {
        "name": "MON",
        "high": 56,
        "precip": 40
      },
      {
        "name": "TUE",
        "high": 51,
        "precip": 98
      },
      {
        "name": "WED",
        "high": 51,
        "precip": 86
      },
      {
        "name": "THU",
        "high": 55,
        "precip": 20
      }
    ]
  },
  "groveland": {
    "label": "Groveland, CA",
    "temp": 42,
    "condition": "Showers And Thunderstorms",
    "emoji": "\u26c8",
    "forecast": [
      {
        "name": "TOD",
        "high": 46,
        "precip": 92
      },
      {
        "name": "MON",
        "high": 53,
        "precip": 19
      },
      {
        "name": "TUE",
        "high": 58,
        "precip": 0
      },
      {
        "name": "WED",
        "high": 59,
        "precip": 3
      },
      {
        "name": "THU",
        "high": 58,
        "precip": 9
      }
    ]
  },
  "deathvalley": {
    "label": "Death Valley, CA",
    "temp": 77,
    "condition": "Patchy Blowing Dust",
    "emoji": "\ud83c\udf21\ufe0f",
    "forecast": [
      {
        "name": "TOD",
        "high": 83,
        "precip": 8
      },
      {
        "name": "MON",
        "high": 77,
        "precip": 24
      },
      {
        "name": "TUE",
        "high": 84,
        "precip": 0
      },
      {
        "name": "WED",
        "high": 89,
        "precip": 0
      },
      {
        "name": "THU",
        "high": 87,
        "precip": 2
      }
    ]
  },
  "updated": "2026-04-12T18:58:05Z"
}