{
  "updated": "2026-06-18T20:32:50Z",
  "articles": [
    {
      "title": "My Six Year Old Rode to School Without Me",
      "link": "https://velo.outsideonline.com/urban/urban-culture/my-six-year-old-rode-to-school-without-me/",
      "date": "Jun 18",
      "source": "VeloNews"
    },
    {
      "title": "14,000 on cycle storage waiting list as bike theft rockets and cyclists complain: \u201cIf you can\u2019t get a space, you\u2019re not going to be inspired to buy a bike\u201d",
      "link": "https://road.cc/news/lambeth-hangar-waiting-list",
      "date": "Jun 18",
      "source": "road.cc"
    },
    {
      "title": "Dispatch from hiatus and update on the future",
      "link": "https://bikeportland.org/2026/06/17/dispatch-from-hiatus-and-update-on-the-future-399986",
      "date": "Jun 17",
      "source": "BikePortland"
    },
    {
      "title": "New Bike Tech: Fashion Forward Designs from Cannondale and Gobik Bring Some Flair for the Summer",
      "link": "https://velo.outsideonline.com/road/road-gear/new-bike-tech-fashion-forward-cannondale-gobik/",
      "date": "Jun 18",
      "source": "VeloNews"
    },
    {
      "title": "Silca Ultimate Tubeless Valves 70mm",
      "link": "https://road.cc/review_v2/silca-ultimate-tubeless-valves-70mm",
      "date": "Jun 18",
      "source": "road.cc"
    },
    {
      "title": "Job: Mechanic \u2013 Metropolis Cycles (FILLED)",
      "link": "https://bikeportland.org/2026/05/20/job-mechanic-metropolis-cycles-399980",
      "date": "May 20",
      "source": "BikePortland"
    },
    {
      "title": "Tour de Suisse Stage 2: UAE Can\u2019t Open a Gift from Poga\u010dar as Breakaway Has Its Day",
      "link": "https://velo.outsideonline.com/road/road-racing/tour-de-suisse-stage-2-uae-cant-open-gift-pogacar/",
      "date": "Jun 18",
      "source": "VeloNews"
    },
    {
      "title": "Could this be the safest road bike ever built? Canyon thinks so",
      "link": "https://road.cc/tech-news/could-this-be-the-safest-road-bike-ever-built-canyon-thinks-so",
      "date": "Jun 18",
      "source": "road.cc"
    },
    {
      "title": "Reminder: No riding through River View Cemetery during Memorial Day Weekend",
      "link": "https://bikeportland.org/2026/05/19/reminder-no-riding-through-river-view-cemetery-during-memorial-day-weekend-399976",
      "date": "May 19",
      "source": "BikePortland"
    },
    {
      "title": "Wout van Aert Nearly Got Sepsis. Here\u2019s How His Tour de France Hopes Ended in a Hospital.",
      "link": "https://velo.outsideonline.com/road/road-racing/van-aert-sepsis-tour-de-france/",
      "date": "Jun 18",
      "source": "VeloNews"
    },
    {
      "title": "GripGrab PACR InsideGrip Full Finger Summer Gloves",
      "link": "https://road.cc/offroad/review_v2/gripgrab-pacr-insidegrip-full-finger-summer-gloves",
      "date": "Jun 18",
      "source": "road.cc"
    },
    {
      "title": "Guest Article: Demand a pause on PBOT\u2019s SW Alder decision",
      "link": "https://bikeportland.org/2026/05/18/guest-article-demand-a-pause-on-pbots-sw-alder-decision-399965",
      "date": "May 18",
      "source": "BikePortland"
    }
  ]
}