{
  "updated": "2026-06-22T13:41:04Z",
  "ytd": {
    "run": {
      "miles": 541.5,
      "time": "118.0h 0.0m",
      "count": 229
    },
    "ride": {
      "miles": 1429.2,
      "time": "105.0h 21.0m",
      "count": 136
    },
    "swim": {
      "yards": 7838,
      "time": "3.0h 7.0m",
      "count": 6
    },
    "yoga": {
      "count": 28,
      "time": "8h 31m"
    },
    "strength": {
      "count": 21,
      "time": "11h 48m"
    }
  },
  "all_time": {
    "run": {
      "miles": 11322.7,
      "count": 2945
    },
    "ride": {
      "miles": 12957.2,
      "count": 1008
    },
    "swim": {
      "yards": 110108,
      "count": 84
    }
  },
  "activities": [
    {
      "id": 19012590690,
      "name": "Morning Run",
      "sport": "Run",
      "icon": "\ud83c\udfc3",
      "distance": "2.0 mi",
      "time": "44:38",
      "pace": "22:14/mi",
      "elevation": "285 ft",
      "date": "Jun 21",
      "kudos": 5,
      "map_url": "https://www.strava.com/activities/19012590690"
    },
    {
      "id": 19002673924,
      "name": "Afternoon Hike",
      "sport": "Hike",
      "icon": "\ud83e\udd7e",
      "distance": "0.6 mi",
      "time": "16:56",
      "pace": "",
      "elevation": "102 ft",
      "date": "Jun 20",
      "kudos": 1,
      "map_url": "https://www.strava.com/activities/19002673924"
    },
    {
      "id": 18999562182,
      "name": "Morning Run",
      "sport": "Run",
      "icon": "\ud83c\udfc3",
      "distance": "5.2 mi",
      "time": "2:07:46",
      "pace": "24:46/mi",
      "elevation": "568 ft",
      "date": "Jun 20",
      "kudos": 5,
      "map_url": "https://www.strava.com/activities/18999562182"
    },
    {
      "id": 18989957822,
      "name": "Afternoon Hike",
      "sport": "Hike",
      "icon": "\ud83e\udd7e",
      "distance": "1.5 mi",
      "time": "32:06",
      "pace": "",
      "elevation": "167 ft",
      "date": "Jun 19",
      "kudos": 5,
      "map_url": "https://www.strava.com/activities/18989957822"
    },
    {
      "id": 18989958751,
      "name": "Lunch Run",
      "sport": "Run",
      "icon": "\ud83c\udfc3",
      "distance": "1.0 mi",
      "time": "1:37:34",
      "pace": "93:02/mi",
      "elevation": "194 ft",
      "date": "Jun 19",
      "kudos": 3,
      "map_url": "https://www.strava.com/activities/18989958751"
    },
    {
      "id": 18984037029,
      "name": "Morning Yoga",
      "sport": "Yoga",
      "icon": "\ud83e\uddd8",
      "distance": "",
      "time": "38:00",
      "pace": "",
      "elevation": "",
      "date": "Jun 19",
      "kudos": 2,
      "map_url": "https://www.strava.com/activities/18984037029"
    },
    {
      "id": 18978740251,
      "name": "Afternoon Hike",
      "sport": "Hike",
      "icon": "\ud83e\udd7e",
      "distance": "1.0 mi",
      "time": "30:04",
      "pace": "",
      "elevation": "121 ft",
      "date": "Jun 18",
      "kudos": 3,
      "map_url": "https://www.strava.com/activities/18978740251"
    },
    {
      "id": 18974753804,
      "name": "Morning Run",
      "sport": "Run",
      "icon": "\ud83c\udfc3",
      "distance": "1.0 mi",
      "time": "1:44:21",
      "pace": "103:03/mi",
      "elevation": "",
      "date": "Jun 18",
      "kudos": 5,
      "map_url": "https://www.strava.com/activities/18974753804"
    },
    {
      "id": 18970957273,
      "name": "Morning Yoga",
      "sport": "Yoga",
      "icon": "\ud83e\uddd8",
      "distance": "",
      "time": "51:39",
      "pace": "",
      "elevation": "",
      "date": "Jun 18",
      "kudos": 5,
      "map_url": "https://www.strava.com/activities/18970957273"
    },
    {
      "id": 18964007738,
      "name": "Afternoon Run",
      "sport": "Run",
      "icon": "\ud83c\udfc3",
      "distance": "4.0 mi",
      "time": "33:09",
      "pace": "8:14/mi",
      "elevation": "",
      "date": "Jun 17",
      "kudos": 4,
      "map_url": "https://www.strava.com/activities/18964007738"
    }
  ]
}